{"loss": 0.6871406052584121, "train_loss": 562984704.645926, "rmse": 0.8289394460968365, "mae": 0.6619393358239836, "r2": 0.2758585825824562, "epoch": 0, "timestamp": 1744188124, "checkpoint_dir_name": null, "done": false, "training_iteration": 1, "trial_id": "92d48f6e", "date": "2025-04-09_03-42-04", "time_this_iter_s": 859.2170822620392, "time_total_s": 859.2170822620392, "pid": 517637, "hostname": "gpua069.delta.ncsa.illinois.edu", "node_ip": "141.142.254.69", "config": {"learning_rate": 0.0017331607338165434, "batch_size": 64, "hidden_dim": 256, "num_layers": 2, "dropout": 0.23487409763750228, "model_type": "gcn"}, "time_since_restore": 859.2170822620392, "iterations_since_restore": 1}
{"loss": 0.6087931165516742, "train_loss": 0.6687608620281269, "rmse": 0.7802519569015804, "mae": 0.6121606999002276, "r2": 0.35842488900079794, "epoch": 1, "timestamp": 1744188823, "checkpoint_dir_name": null, "done": false, "training_iteration": 2, "trial_id": "92d48f6e", "date": "2025-04-09_03-53-43", "time_this_iter_s": 698.7822027206421, "time_total_s": 1557.9992849826813, "pid": 517637, "hostname": "gpua069.delta.ncsa.illinois.edu", "node_ip": "141.142.254.69", "config": {"learning_rate": 0.0017331607338165434, "batch_size": 64, "hidden_dim": 256, "num_layers": 2, "dropout": 0.23487409763750228, "model_type": "gcn"}, "time_since_restore": 1557.9992849826813, "iterations_since_restore": 2}
{"loss": 0.6133368677292405, "train_loss": 0.652526544460111, "rmse": 0.7831582646863654, "mae": 0.6168084307408488, "r2": 0.3536364679995717, "epoch": 2, "timestamp": 1744189515, "checkpoint_dir_name": null, "done": false, "training_iteration": 3, "trial_id": "92d48f6e", "date": "2025-04-09_04-05-15", "time_this_iter_s": 691.6843276023865, "time_total_s": 2249.6836125850677, "pid": 517637, "hostname": "gpua069.delta.ncsa.illinois.edu", "node_ip": "141.142.254.69", "config": {"learning_rate": 0.0017331607338165434, "batch_size": 64, "hidden_dim": 256, "num_layers": 2, "dropout": 0.23487409763750228, "model_type": "gcn"}, "time_since_restore": 2249.6836125850677, "iterations_since_restore": 3}
{"loss": 0.6127155527970246, "train_loss": 0.6488187025880565, "rmse": 0.782761491981023, "mae": 0.6189033286767148, "r2": 0.3542912384427146, "epoch": 3, "timestamp": 1744190139, "checkpoint_dir_name": null, "done": false, "training_iteration": 4, "trial_id": "92d48f6e", "date": "2025-04-09_04-15-39", "time_this_iter_s": 624.2058987617493, "time_total_s": 2873.889511346817, "pid": 517637, "hostname": "gpua069.delta.ncsa.illinois.edu", "node_ip": "141.142.254.69", "config": {"learning_rate": 0.0017331607338165434, "batch_size": 64, "hidden_dim": 256, "num_layers": 2, "dropout": 0.23487409763750228, "model_type": "gcn"}, "time_since_restore": 2873.889511346817, "iterations_since_restore": 4}
{"loss": 0.5980135987076411, "train_loss": 0.6452077502034302, "rmse": 0.7733133895797714, "mae": 0.6078621927277444, "r2": 0.3697848569594222, "epoch": 4, "timestamp": 1744190832, "checkpoint_dir_name": null, "done": false, "training_iteration": 5, "trial_id": "92d48f6e", "date": "2025-04-09_04-27-12", "time_this_iter_s": 693.2596590518951, "time_total_s": 3567.149170398712, "pid": 517637, "hostname": "gpua069.delta.ncsa.illinois.edu", "node_ip": "141.142.254.69", "config": {"learning_rate": 0.0017331607338165434, "batch_size": 64, "hidden_dim": 256, "num_layers": 2, "dropout": 0.23487409763750228, "model_type": "gcn"}, "time_since_restore": 3567.149170398712, "iterations_since_restore": 5}
{"loss": 0.5968679787976148, "train_loss": 0.64467777014681, "rmse": 0.7725723128811717, "mae": 0.6039020345730716, "r2": 0.37099216561228365, "epoch": 5, "timestamp": 1744191527, "checkpoint_dir_name": null, "done": false, "training_iteration": 6, "trial_id": "92d48f6e", "date": "2025-04-09_04-38-47", "time_this_iter_s": 694.9062163829803, "time_total_s": 4262.0553867816925, "pid": 517637, "hostname": "gpua069.delta.ncsa.illinois.edu", "node_ip": "141.142.254.69", "config": {"learning_rate": 0.0017331607338165434, "batch_size": 64, "hidden_dim": 256, "num_layers": 2, "dropout": 0.23487409763750228, "model_type": "gcn"}, "time_since_restore": 4262.0553867816925, "iterations_since_restore": 6}
{"loss": 0.6014730547548572, "train_loss": 0.64405675186373, "rmse": 0.7755469390537298, "mae": 0.6114527427592138, "r2": 0.36613911767874974, "epoch": 6, "timestamp": 1744192222, "checkpoint_dir_name": null, "done": false, "training_iteration": 7, "trial_id": "92d48f6e", "date": "2025-04-09_04-50-22", "time_this_iter_s": 694.6447288990021, "time_total_s": 4956.700115680695, "pid": 517637, "hostname": "gpua069.delta.ncsa.illinois.edu", "node_ip": "141.142.254.69", "config": {"learning_rate": 0.0017331607338165434, "batch_size": 64, "hidden_dim": 256, "num_layers": 2, "dropout": 0.23487409763750228, "model_type": "gcn"}, "time_since_restore": 4956.700115680695, "iterations_since_restore": 7}
{"loss": 0.597422064444276, "train_loss": 0.6433781015211696, "rmse": 0.7729308279370604, "mae": 0.6066621429583398, "r2": 0.370408243306933, "epoch": 7, "timestamp": 1744192852, "checkpoint_dir_name": null, "done": false, "training_iteration": 8, "trial_id": "92d48f6e", "date": "2025-04-09_05-00-52", "time_this_iter_s": 629.757089138031, "time_total_s": 5586.457204818726, "pid": 517637, "hostname": "gpua069.delta.ncsa.illinois.edu", "node_ip": "141.142.254.69", "config": {"learning_rate": 0.0017331607338165434, "batch_size": 64, "hidden_dim": 256, "num_layers": 2, "dropout": 0.23487409763750228, "model_type": "gcn"}, "time_since_restore": 5586.457204818726, "iterations_since_restore": 8}
{"loss": 0.5932814181712399, "train_loss": 0.642337741167032, "rmse": 0.7702476345385819, "mae": 0.604848777654943, "r2": 0.3747718530702675, "epoch": 8, "timestamp": 1744193528, "checkpoint_dir_name": null, "done": false, "training_iteration": 9, "trial_id": "92d48f6e", "date": "2025-04-09_05-12-08", "time_this_iter_s": 675.9221696853638, "time_total_s": 6262.379374504089, "pid": 517637, "hostname": "gpua069.delta.ncsa.illinois.edu", "node_ip": "141.142.254.69", "config": {"learning_rate": 0.0017331607338165434, "batch_size": 64, "hidden_dim": 256, "num_layers": 2, "dropout": 0.23487409763750228, "model_type": "gcn"}, "time_since_restore": 6262.379374504089, "iterations_since_restore": 9}
{"loss": 0.6006056196334886, "train_loss": 0.6411323054296295, "rmse": 0.7749874967421824, "mae": 0.6085848563913594, "r2": 0.3670532614411709, "epoch": 9, "timestamp": 1744194206, "checkpoint_dir_name": null, "done": false, "training_iteration": 10, "trial_id": "92d48f6e", "date": "2025-04-09_05-23-26", "time_this_iter_s": 678.1833658218384, "time_total_s": 6940.562740325928, "pid": 517637, "hostname": "gpua069.delta.ncsa.illinois.edu", "node_ip": "141.142.254.69", "config": {"learning_rate": 0.0017331607338165434, "batch_size": 64, "hidden_dim": 256, "num_layers": 2, "dropout": 0.23487409763750228, "model_type": "gcn"}, "time_since_restore": 6940.562740325928, "iterations_since_restore": 10}
{"loss": 0.5981955052404648, "train_loss": 0.6402156783101375, "rmse": 0.7734309958986484, "mae": 0.609490805393716, "r2": 0.369593154811264, "epoch": 10, "timestamp": 1744194900, "checkpoint_dir_name": null, "done": false, "training_iteration": 11, "trial_id": "92d48f6e", "date": "2025-04-09_05-35-00", "time_this_iter_s": 693.8489108085632, "time_total_s": 7634.411651134491, "pid": 517637, "hostname": "gpua069.delta.ncsa.illinois.edu", "node_ip": "141.142.254.69", "config": {"learning_rate": 0.0017331607338165434, "batch_size": 64, "hidden_dim": 256, "num_layers": 2, "dropout": 0.23487409763750228, "model_type": "gcn"}, "time_since_restore": 7634.411651134491, "iterations_since_restore": 11}
{"loss": 0.602423273409066, "train_loss": 0.640216040766363, "rmse": 0.7761593091511455, "mae": 0.614084131820283, "r2": 0.36513773226976765, "epoch": 11, "timestamp": 1744195526, "checkpoint_dir_name": null, "done": false, "training_iteration": 12, "trial_id": "92d48f6e", "date": "2025-04-09_05-45-26", "time_this_iter_s": 625.926438331604, "time_total_s": 8260.338089466095, "pid": 517637, "hostname": "gpua069.delta.ncsa.illinois.edu", "node_ip": "141.142.254.69", "config": {"learning_rate": 0.0017331607338165434, "batch_size": 64, "hidden_dim": 256, "num_layers": 2, "dropout": 0.23487409763750228, "model_type": "gcn"}, "time_since_restore": 8260.338089466095, "iterations_since_restore": 12}
{"loss": 0.5954809510527155, "train_loss": 0.6398850393356703, "rmse": 0.7716741224718, "mae": 0.6044201121000607, "r2": 0.3724538809217164, "epoch": 12, "timestamp": 1744196228, "checkpoint_dir_name": null, "done": false, "training_iteration": 13, "trial_id": "92d48f6e", "date": "2025-04-09_05-57-08", "time_this_iter_s": 702.7559244632721, "time_total_s": 8963.094013929367, "pid": 517637, "hostname": "gpua069.delta.ncsa.illinois.edu", "node_ip": "141.142.254.69", "config": {"learning_rate": 0.0017331607338165434, "batch_size": 64, "hidden_dim": 256, "num_layers": 2, "dropout": 0.23487409763750228, "model_type": "gcn"}, "time_since_restore": 8963.094013929367, "iterations_since_restore": 13}
{"loss": 0.6019627385072025, "train_loss": 0.6399140682835223, "rmse": 0.7758625770651425, "mae": 0.609595886577605, "r2": 0.36562306560902025, "epoch": 13, "timestamp": 1744196940, "checkpoint_dir_name": null, "done": false, "training_iteration": 14, "trial_id": "92d48f6e", "date": "2025-04-09_06-09-00", "time_this_iter_s": 711.5826554298401, "time_total_s": 9674.676669359207, "pid": 517637, "hostname": "gpua069.delta.ncsa.illinois.edu", "node_ip": "141.142.254.69", "config": {"learning_rate": 0.0017331607338165434, "batch_size": 64, "hidden_dim": 256, "num_layers": 2, "dropout": 0.23487409763750228, "model_type": "gcn"}, "time_since_restore": 9674.676669359207, "iterations_since_restore": 14}
{"loss": 0.5941717788400402, "train_loss": 0.6395638884144729, "rmse": 0.7708253880978262, "mae": 0.6049782825064434, "r2": 0.37383354895260223, "epoch": 14, "timestamp": 1744197651, "checkpoint_dir_name": null, "done": false, "training_iteration": 15, "trial_id": "92d48f6e", "date": "2025-04-09_06-20-51", "time_this_iter_s": 711.3337509632111, "time_total_s": 10386.010420322418, "pid": 517637, "hostname": "gpua069.delta.ncsa.illinois.edu", "node_ip": "141.142.254.69", "config": {"learning_rate": 0.0017331607338165434, "batch_size": 64, "hidden_dim": 256, "num_layers": 2, "dropout": 0.23487409763750228, "model_type": "gcn"}, "time_since_restore": 10386.010420322418, "iterations_since_restore": 15}
{"loss": 0.5953433551341633, "train_loss": 0.6392629419827894, "rmse": 0.7715849631776449, "mae": 0.6031901109359208, "r2": 0.37259888600889757, "epoch": 15, "timestamp": 1744198282, "checkpoint_dir_name": null, "done": false, "training_iteration": 16, "trial_id": "92d48f6e", "date": "2025-04-09_06-31-22", "time_this_iter_s": 630.2292063236237, "time_total_s": 11016.239626646042, "pid": 517637, "hostname": "gpua069.delta.ncsa.illinois.edu", "node_ip": "141.142.254.69", "config": {"learning_rate": 0.0017331607338165434, "batch_size": 64, "hidden_dim": 256, "num_layers": 2, "dropout": 0.23487409763750228, "model_type": "gcn"}, "time_since_restore": 11016.239626646042, "iterations_since_restore": 16}
{"loss": 0.6023126877320893, "train_loss": 0.6392087725997703, "rmse": 0.7760880669684914, "mae": 0.6057860641257736, "r2": 0.36525427251444165, "epoch": 16, "timestamp": 1744198986, "checkpoint_dir_name": null, "done": false, "training_iteration": 17, "trial_id": "92d48f6e", "date": "2025-04-09_06-43-06", "time_this_iter_s": 704.0709331035614, "time_total_s": 11720.310559749603, "pid": 517637, "hostname": "gpua069.delta.ncsa.illinois.edu", "node_ip": "141.142.254.69", "config": {"learning_rate": 0.0017331607338165434, "batch_size": 64, "hidden_dim": 256, "num_layers": 2, "dropout": 0.23487409763750228, "model_type": "gcn"}, "time_since_restore": 11720.310559749603, "iterations_since_restore": 17}
{"loss": 0.5911565659164254, "train_loss": 0.6393783395395297, "rmse": 0.7688670666634521, "mae": 0.6028042872562493, "r2": 0.3770111233936998, "epoch": 17, "timestamp": 1744199693, "checkpoint_dir_name": null, "done": false, "training_iteration": 18, "trial_id": "92d48f6e", "date": "2025-04-09_06-54-53", "time_this_iter_s": 706.9483478069305, "time_total_s": 12427.258907556534, "pid": 517637, "hostname": "gpua069.delta.ncsa.illinois.edu", "node_ip": "141.142.254.69", "config": {"learning_rate": 0.0017331607338165434, "batch_size": 64, "hidden_dim": 256, "num_layers": 2, "dropout": 0.23487409763750228, "model_type": "gcn"}, "time_since_restore": 12427.258907556534, "iterations_since_restore": 18}
{"loss": 0.5933958550108407, "train_loss": 0.6392251914850563, "rmse": 0.7703219165683939, "mae": 0.6044656011587669, "r2": 0.3746512543089363, "epoch": 18, "timestamp": 1744200400, "checkpoint_dir_name": null, "done": false, "training_iteration": 19, "trial_id": "92d48f6e", "date": "2025-04-09_07-06-40", "time_this_iter_s": 707.9057977199554, "time_total_s": 13135.16470527649, "pid": 517637, "hostname": "gpua069.delta.ncsa.illinois.edu", "node_ip": "141.142.254.69", "config": {"learning_rate": 0.0017331607338165434, "batch_size": 64, "hidden_dim": 256, "num_layers": 2, "dropout": 0.23487409763750228, "model_type": "gcn"}, "time_since_restore": 13135.16470527649, "iterations_since_restore": 19}
{"loss": 0.5910440986869235, "train_loss": 0.6392287665404589, "rmse": 0.7687939248733989, "mae": 0.6005168948842682, "r2": 0.3771296467542077, "epoch": 19, "timestamp": 1744201030, "checkpoint_dir_name": null, "done": false, "training_iteration": 20, "trial_id": "92d48f6e", "date": "2025-04-09_07-17-10", "time_this_iter_s": 629.4617047309875, "time_total_s": 13764.626410007477, "pid": 517637, "hostname": "gpua069.delta.ncsa.illinois.edu", "node_ip": "141.142.254.69", "config": {"learning_rate": 0.0017331607338165434, "batch_size": 64, "hidden_dim": 256, "num_layers": 2, "dropout": 0.23487409763750228, "model_type": "gcn"}, "time_since_restore": 13764.626410007477, "iterations_since_restore": 20}
{"loss": 0.5932729096773925, "train_loss": 0.6392466214365469, "rmse": 0.770242111071358, "mae": 0.6032914878263753, "r2": 0.37478082009500047, "epoch": 20, "timestamp": 1744201736, "checkpoint_dir_name": null, "done": false, "training_iteration": 21, "trial_id": "92d48f6e", "date": "2025-04-09_07-28-56", "time_this_iter_s": 705.8802978992462, "time_total_s": 14470.506707906723, "pid": 517637, "hostname": "gpua069.delta.ncsa.illinois.edu", "node_ip": "141.142.254.69", "config": {"learning_rate": 0.0017331607338165434, "batch_size": 64, "hidden_dim": 256, "num_layers": 2, "dropout": 0.23487409763750228, "model_type": "gcn"}, "time_since_restore": 14470.506707906723, "iterations_since_restore": 21}
{"loss": 0.5963890725868128, "train_loss": 0.6390922638164221, "rmse": 0.7722623083591497, "mae": 0.6017553945513777, "r2": 0.37149685921215325, "epoch": 21, "timestamp": 1744202439, "checkpoint_dir_name": null, "done": false, "training_iteration": 22, "trial_id": "92d48f6e", "date": "2025-04-09_07-40-39", "time_this_iter_s": 703.1095507144928, "time_total_s": 15173.616258621216, "pid": 517637, "hostname": "gpua069.delta.ncsa.illinois.edu", "node_ip": "141.142.254.69", "config": {"learning_rate": 0.0017331607338165434, "batch_size": 64, "hidden_dim": 256, "num_layers": 2, "dropout": 0.23487409763750228, "model_type": "gcn"}, "time_since_restore": 15173.616258621216, "iterations_since_restore": 22}
{"loss": 0.591273328574958, "train_loss": 0.6392772234202733, "rmse": 0.7689429943562819, "mae": 0.603465035224818, "r2": 0.37688807366061683, "epoch": 22, "timestamp": 1744203133, "checkpoint_dir_name": null, "done": false, "training_iteration": 23, "trial_id": "92d48f6e", "date": "2025-04-09_07-52-13", "time_this_iter_s": 694.1229853630066, "time_total_s": 15867.739243984222, "pid": 517637, "hostname": "gpua069.delta.ncsa.illinois.edu", "node_ip": "141.142.254.69", "config": {"learning_rate": 0.0017331607338165434, "batch_size": 64, "hidden_dim": 256, "num_layers": 2, "dropout": 0.23487409763750228, "model_type": "gcn"}, "time_since_restore": 15867.739243984222, "iterations_since_restore": 23}
{"loss": 0.5933792511218163, "train_loss": 0.6389853302806691, "rmse": 0.7703111393034362, "mae": 0.6041529538687422, "r2": 0.3746687521934783, "epoch": 23, "timestamp": 1744203781, "checkpoint_dir_name": null, "done": false, "training_iteration": 24, "trial_id": "92d48f6e", "date": "2025-04-09_08-03-01", "time_this_iter_s": 648.3808419704437, "time_total_s": 16516.120085954666, "pid": 517637, "hostname": "gpua069.delta.ncsa.illinois.edu", "node_ip": "141.142.254.69", "config": {"learning_rate": 0.0017331607338165434, "batch_size": 64, "hidden_dim": 256, "num_layers": 2, "dropout": 0.23487409763750228, "model_type": "gcn"}, "time_since_restore": 16516.120085954666, "iterations_since_restore": 24}
{"loss": 0.6030560064582315, "train_loss": 0.6391609228605168, "rmse": 0.7765668074407251, "mae": 0.607573638477461, "r2": 0.36447092792239266, "epoch": 24, "timestamp": 1744204465, "checkpoint_dir_name": null, "done": false, "training_iteration": 25, "trial_id": "92d48f6e", "date": "2025-04-09_08-14-25", "time_this_iter_s": 683.6713762283325, "time_total_s": 17199.791462183, "pid": 517637, "hostname": "gpua069.delta.ncsa.illinois.edu", "node_ip": "141.142.254.69", "config": {"learning_rate": 0.0017331607338165434, "batch_size": 64, "hidden_dim": 256, "num_layers": 2, "dropout": 0.23487409763750228, "model_type": "gcn"}, "time_since_restore": 17199.791462183, "iterations_since_restore": 25}
{"loss": 0.5902254331456499, "train_loss": 0.6393190372865403, "rmse": 0.7682613053623008, "mae": 0.5987964407510841, "r2": 0.37799239546562835, "epoch": 25, "timestamp": 1744205126, "checkpoint_dir_name": null, "done": false, "training_iteration": 26, "trial_id": "92d48f6e", "date": "2025-04-09_08-25-26", "time_this_iter_s": 661.0559043884277, "time_total_s": 17860.847366571426, "pid": 517637, "hostname": "gpua069.delta.ncsa.illinois.edu", "node_ip": "141.142.254.69", "config": {"learning_rate": 0.0017331607338165434, "batch_size": 64, "hidden_dim": 256, "num_layers": 2, "dropout": 0.23487409763750228, "model_type": "gcn"}, "time_since_restore": 17860.847366571426, "iterations_since_restore": 26}
{"loss": 0.592747024480129, "train_loss": 0.6390363705075655, "rmse": 0.7699006587844653, "mae": 0.602196274733841, "r2": 0.3753350229794463, "epoch": 26, "timestamp": 1744205787, "checkpoint_dir_name": null, "done": false, "training_iteration": 27, "trial_id": "92d48f6e", "date": "2025-04-09_08-36-27", "time_this_iter_s": 660.3708868026733, "time_total_s": 18521.2182533741, "pid": 517637, "hostname": "gpua069.delta.ncsa.illinois.edu", "node_ip": "141.142.254.69", "config": {"learning_rate": 0.0017331607338165434, "batch_size": 64, "hidden_dim": 256, "num_layers": 2, "dropout": 0.23487409763750228, "model_type": "gcn"}, "time_since_restore": 18521.2182533741, "iterations_since_restore": 27}
{"loss": 0.5944607019835001, "train_loss": 0.6393308847064737, "rmse": 0.7710127767585889, "mae": 0.6069749112058334, "r2": 0.3735290681796132, "epoch": 27, "timestamp": 1744206407, "checkpoint_dir_name": null, "done": false, "training_iteration": 28, "trial_id": "92d48f6e", "date": "2025-04-09_08-46-47", "time_this_iter_s": 619.9505021572113, "time_total_s": 19141.16875553131, "pid": 517637, "hostname": "gpua069.delta.ncsa.illinois.edu", "node_ip": "141.142.254.69", "config": {"learning_rate": 0.0017331607338165434, "batch_size": 64, "hidden_dim": 256, "num_layers": 2, "dropout": 0.23487409763750228, "model_type": "gcn"}, "time_since_restore": 19141.16875553131, "iterations_since_restore": 28}
{"loss": 0.5931292253948687, "train_loss": 0.6383605807292484, "rmse": 0.7701488331435339, "mae": 0.6036644987444728, "r2": 0.37493224162185235, "epoch": 28, "timestamp": 1744207066, "checkpoint_dir_name": null, "done": false, "training_iteration": 29, "trial_id": "92d48f6e", "date": "2025-04-09_08-57-46", "time_this_iter_s": 659.5460801124573, "time_total_s": 19800.71483564377, "pid": 517637, "hostname": "gpua069.delta.ncsa.illinois.edu", "node_ip": "141.142.254.69", "config": {"learning_rate": 0.0017331607338165434, "batch_size": 64, "hidden_dim": 256, "num_layers": 2, "dropout": 0.23487409763750228, "model_type": "gcn"}, "time_since_restore": 19800.71483564377, "iterations_since_restore": 29}
{"loss": 0.5915426969120983, "train_loss": 0.6379068883971467, "rmse": 0.7691181293415603, "mae": 0.6017507651139699, "r2": 0.3766042005348821, "epoch": 29, "timestamp": 1744207729, "checkpoint_dir_name": null, "done": false, "training_iteration": 30, "trial_id": "92d48f6e", "date": "2025-04-09_09-08-49", "time_this_iter_s": 663.0029604434967, "time_total_s": 20463.717796087265, "pid": 517637, "hostname": "gpua069.delta.ncsa.illinois.edu", "node_ip": "141.142.254.69", "config": {"learning_rate": 0.0017331607338165434, "batch_size": 64, "hidden_dim": 256, "num_layers": 2, "dropout": 0.23487409763750228, "model_type": "gcn"}, "time_since_restore": 20463.717796087265, "iterations_since_restore": 30}
{"loss": 0.5925969608391144, "train_loss": 0.6377561375813742, "rmse": 0.769803195928531, "mae": 0.6027645122237791, "r2": 0.3754931674839881, "epoch": 30, "timestamp": 1744208390, "checkpoint_dir_name": null, "done": false, "training_iteration": 31, "trial_id": "92d48f6e", "date": "2025-04-09_09-19-50", "time_this_iter_s": 660.6414754390717, "time_total_s": 21124.359271526337, "pid": 517637, "hostname": "gpua069.delta.ncsa.illinois.edu", "node_ip": "141.142.254.69", "config": {"learning_rate": 0.0017331607338165434, "batch_size": 64, "hidden_dim": 256, "num_layers": 2, "dropout": 0.23487409763750228, "model_type": "gcn"}, "time_since_restore": 21124.359271526337, "iterations_since_restore": 31}
{"loss": 0.5946735785766533, "train_loss": 0.6378286657611899, "rmse": 0.7711508145169419, "mae": 0.6009256100695765, "r2": 0.3733047284880988, "epoch": 31, "timestamp": 1744209011, "checkpoint_dir_name": null, "done": false, "training_iteration": 32, "trial_id": "92d48f6e", "date": "2025-04-09_09-30-11", "time_this_iter_s": 621.5549669265747, "time_total_s": 21745.91423845291, "pid": 517637, "hostname": "gpua069.delta.ncsa.illinois.edu", "node_ip": "141.142.254.69", "config": {"learning_rate": 0.0017331607338165434, "batch_size": 64, "hidden_dim": 256, "num_layers": 2, "dropout": 0.23487409763750228, "model_type": "gcn"}, "time_since_restore": 21745.91423845291, "iterations_since_restore": 32}
{"loss": 0.5923970408630221, "train_loss": 0.6379160758251265, "rmse": 0.7696733338002133, "mae": 0.5999858775483619, "r2": 0.3757038523610444, "epoch": 32, "timestamp": 1744209678, "checkpoint_dir_name": null, "done": false, "training_iteration": 33, "trial_id": "92d48f6e", "date": "2025-04-09_09-41-18", "time_this_iter_s": 666.9386649131775, "time_total_s": 22412.85290336609, "pid": 517637, "hostname": "gpua069.delta.ncsa.illinois.edu", "node_ip": "141.142.254.69", "config": {"learning_rate": 0.0017331607338165434, "batch_size": 64, "hidden_dim": 256, "num_layers": 2, "dropout": 0.23487409763750228, "model_type": "gcn"}, "time_since_restore": 22412.85290336609, "iterations_since_restore": 33}
{"loss": 0.5927609467036498, "train_loss": 0.6380033895952504, "rmse": 0.7699097003063029, "mae": 0.6013366893086358, "r2": 0.37532035107306383, "epoch": 33, "timestamp": 1744210338, "checkpoint_dir_name": null, "done": false, "training_iteration": 34, "trial_id": "92d48f6e", "date": "2025-04-09_09-52-18", "time_this_iter_s": 659.8967800140381, "time_total_s": 23072.749683380127, "pid": 517637, "hostname": "gpua069.delta.ncsa.illinois.edu", "node_ip": "141.142.254.69", "config": {"learning_rate": 0.0017331607338165434, "batch_size": 64, "hidden_dim": 256, "num_layers": 2, "dropout": 0.23487409763750228, "model_type": "gcn"}, "time_since_restore": 23072.749683380127, "iterations_since_restore": 34}
{"loss": 0.5889164452474213, "train_loss": 0.638002206142765, "rmse": 0.7674089163610021, "mae": 0.6021158174875844, "r2": 0.37937186964143366, "epoch": 34, "timestamp": 1744210996, "checkpoint_dir_name": null, "done": false, "training_iteration": 35, "trial_id": "92d48f6e", "date": "2025-04-09_10-03-16", "time_this_iter_s": 657.5713155269623, "time_total_s": 23730.32099890709, "pid": 517637, "hostname": "gpua069.delta.ncsa.illinois.edu", "node_ip": "141.142.254.69", "config": {"learning_rate": 0.0017331607338165434, "batch_size": 64, "hidden_dim": 256, "num_layers": 2, "dropout": 0.23487409763750228, "model_type": "gcn"}, "time_since_restore": 23730.32099890709, "iterations_since_restore": 35}
{"loss": 0.5893376738798515, "train_loss": 0.6379412303293021, "rmse": 0.7676833161590314, "mae": 0.5984901993371915, "r2": 0.37892795850923744, "epoch": 35, "timestamp": 1744211617, "checkpoint_dir_name": null, "done": false, "training_iteration": 36, "trial_id": "92d48f6e", "date": "2025-04-09_10-13-37", "time_this_iter_s": 621.3292946815491, "time_total_s": 24351.65029358864, "pid": 517637, "hostname": "gpua069.delta.ncsa.illinois.edu", "node_ip": "141.142.254.69", "config": {"learning_rate": 0.0017331607338165434, "batch_size": 64, "hidden_dim": 256, "num_layers": 2, "dropout": 0.23487409763750228, "model_type": "gcn"}, "time_since_restore": 24351.65029358864, "iterations_since_restore": 36}
{"loss": 0.5929744917849746, "train_loss": 0.6379058647447128, "rmse": 0.7700483697920327, "mae": 0.602303176600147, "r2": 0.3750953070020201, "epoch": 36, "timestamp": 1744212282, "checkpoint_dir_name": null, "done": false, "training_iteration": 37, "trial_id": "92d48f6e", "date": "2025-04-09_10-24-42", "time_this_iter_s": 665.1922197341919, "time_total_s": 25016.84251332283, "pid": 517637, "hostname": "gpua069.delta.ncsa.illinois.edu", "node_ip": "141.142.254.69", "config": {"learning_rate": 0.0017331607338165434, "batch_size": 64, "hidden_dim": 256, "num_layers": 2, "dropout": 0.23487409763750228, "model_type": "gcn"}, "time_since_restore": 25016.84251332283, "iterations_since_restore": 37}
{"loss": 0.59257063114614, "train_loss": 0.6379374985446756, "rmse": 0.7697860943800475, "mae": 0.6036975059595231, "r2": 0.3755209146154628, "epoch": 37, "timestamp": 1744212948, "checkpoint_dir_name": null, "done": false, "training_iteration": 38, "trial_id": "92d48f6e", "date": "2025-04-09_10-35-48", "time_this_iter_s": 665.8548657894135, "time_total_s": 25682.697379112244, "pid": 517637, "hostname": "gpua069.delta.ncsa.illinois.edu", "node_ip": "141.142.254.69", "config": {"learning_rate": 0.0017331607338165434, "batch_size": 64, "hidden_dim": 256, "num_layers": 2, "dropout": 0.23487409763750228, "model_type": "gcn"}, "time_since_restore": 25682.697379112244, "iterations_since_restore": 38}
{"loss": 0.5935704739316001, "train_loss": 0.6379066996423391, "rmse": 0.770435249469316, "mae": 0.602839654196029, "r2": 0.37446723305900276, "epoch": 38, "timestamp": 1744213608, "checkpoint_dir_name": null, "done": false, "training_iteration": 39, "trial_id": "92d48f6e", "date": "2025-04-09_10-46-48", "time_this_iter_s": 659.7566428184509, "time_total_s": 26342.454021930695, "pid": 517637, "hostname": "gpua069.delta.ncsa.illinois.edu", "node_ip": "141.142.254.69", "config": {"learning_rate": 0.0017331607338165434, "batch_size": 64, "hidden_dim": 256, "num_layers": 2, "dropout": 0.23487409763750228, "model_type": "gcn"}, "time_since_restore": 26342.454021930695, "iterations_since_restore": 39}
{"loss": 0.5905253323328274, "train_loss": 0.6376069173064297, "rmse": 0.76845646108644, "mae": 0.6020074351034675, "r2": 0.3776763473676016, "epoch": 39, "timestamp": 1744214225, "checkpoint_dir_name": null, "done": false, "training_iteration": 40, "trial_id": "92d48f6e", "date": "2025-04-09_10-57-05", "time_this_iter_s": 617.4229030609131, "time_total_s": 26959.876924991608, "pid": 517637, "hostname": "gpua069.delta.ncsa.illinois.edu", "node_ip": "141.142.254.69", "config": {"learning_rate": 0.0017331607338165434, "batch_size": 64, "hidden_dim": 256, "num_layers": 2, "dropout": 0.23487409763750228, "model_type": "gcn"}, "time_since_restore": 26959.876924991608, "iterations_since_restore": 40}
{"loss": 0.5980420213380654, "train_loss": 0.637968689321042, "rmse": 0.77333176678152, "mae": 0.606461518890373, "r2": 0.36975490344096873, "epoch": 40, "timestamp": 1744214893, "checkpoint_dir_name": null, "done": false, "training_iteration": 41, "trial_id": "92d48f6e", "date": "2025-04-09_11-08-13", "time_this_iter_s": 667.3762617111206, "time_total_s": 27627.25318670273, "pid": 517637, "hostname": "gpua069.delta.ncsa.illinois.edu", "node_ip": "141.142.254.69", "config": {"learning_rate": 0.0017331607338165434, "batch_size": 64, "hidden_dim": 256, "num_layers": 2, "dropout": 0.23487409763750228, "model_type": "gcn"}, "time_since_restore": 27627.25318670273, "iterations_since_restore": 41}
{"loss": 0.5945680376337719, "train_loss": 0.6378819759694122, "rmse": 0.7710823806780269, "mae": 0.6048866029499727, "r2": 0.37341595254309645, "epoch": 41, "timestamp": 1744215552, "checkpoint_dir_name": null, "done": false, "training_iteration": 42, "trial_id": "92d48f6e", "date": "2025-04-09_11-19-12", "time_this_iter_s": 659.2613105773926, "time_total_s": 28286.51449728012, "pid": 517637, "hostname": "gpua069.delta.ncsa.illinois.edu", "node_ip": "141.142.254.69", "config": {"learning_rate": 0.0017331607338165434, "batch_size": 64, "hidden_dim": 256, "num_layers": 2, "dropout": 0.23487409763750228, "model_type": "gcn"}, "time_since_restore": 28286.51449728012, "iterations_since_restore": 42}
{"loss": 0.5974717697838534, "train_loss": 0.6379633430357606, "rmse": 0.7729629810517478, "mae": 0.6050963393728549, "r2": 0.37035586149919997, "epoch": 42, "timestamp": 1744216213, "checkpoint_dir_name": null, "done": false, "training_iteration": 43, "trial_id": "92d48f6e", "date": "2025-04-09_11-30-13", "time_this_iter_s": 660.9441108703613, "time_total_s": 28947.458608150482, "pid": 517637, "hostname": "gpua069.delta.ncsa.illinois.edu", "node_ip": "141.142.254.69", "config": {"learning_rate": 0.0017331607338165434, "batch_size": 64, "hidden_dim": 256, "num_layers": 2, "dropout": 0.23487409763750228, "model_type": "gcn"}, "time_since_restore": 28947.458608150482, "iterations_since_restore": 43}
{"loss": 0.5918642695565384, "train_loss": 0.6376535745032279, "rmse": 0.7693271535358219, "mae": 0.6051548974472211, "r2": 0.3762653123816393, "epoch": 43, "timestamp": 1744216832, "checkpoint_dir_name": null, "done": false, "training_iteration": 44, "trial_id": "92d48f6e", "date": "2025-04-09_11-40-32", "time_this_iter_s": 619.3243143558502, "time_total_s": 29566.782922506332, "pid": 517637, "hostname": "gpua069.delta.ncsa.illinois.edu", "node_ip": "141.142.254.69", "config": {"learning_rate": 0.0017331607338165434, "batch_size": 64, "hidden_dim": 256, "num_layers": 2, "dropout": 0.23487409763750228, "model_type": "gcn"}, "time_since_restore": 29566.782922506332, "iterations_since_restore": 44}
{"loss": 0.5910054174192507, "train_loss": 0.6377576782036756, "rmse": 0.768768767194708, "mae": 0.6034040413673041, "r2": 0.3771704111653652, "epoch": 44, "timestamp": 1744217496, "checkpoint_dir_name": null, "done": false, "training_iteration": 45, "trial_id": "92d48f6e", "date": "2025-04-09_11-51-36", "time_this_iter_s": 663.7814638614655, "time_total_s": 30230.564386367798, "pid": 517637, "hostname": "gpua069.delta.ncsa.illinois.edu", "node_ip": "141.142.254.69", "config": {"learning_rate": 0.0017331607338165434, "batch_size": 64, "hidden_dim": 256, "num_layers": 2, "dropout": 0.23487409763750228, "model_type": "gcn"}, "time_since_restore": 30230.564386367798, "iterations_since_restore": 45}
